natsio/__init__.py
natsio/const.py
natsio/py.typed
natsio/abc/__init__.py
natsio/abc/client.py
natsio/abc/connection.py
natsio/abc/dispatcher.py
natsio/abc/protocol.py
natsio/client/__init__.py
natsio/client/config.py
natsio/client/core.py
natsio/client/status.py
natsio/connection/__init__.py
natsio/connection/protocol.py
natsio/connection/status.py
natsio/connection/stream.py
natsio/connection/tcp.py
natsio/exceptions/__init__.py
natsio/exceptions/base.py
natsio/exceptions/client.py
natsio/exceptions/connection.py
natsio/exceptions/protocol.py
natsio/exceptions/stream.py
natsio/exceptions/subscription.py
natsio/messages/__init__.py
natsio/messages/core.py
natsio/messages/dispatcher.py
natsio/protocol/__init__.py
natsio/protocol/parser.py
natsio/protocol/operations/__init__.py
natsio/protocol/operations/connect.py
natsio/protocol/operations/err.py
natsio/protocol/operations/hmsg.py
natsio/protocol/operations/hpub.py
natsio/protocol/operations/info.py
natsio/protocol/operations/msg.py
natsio/protocol/operations/ok.py
natsio/protocol/operations/ping_pong.py
natsio/protocol/operations/pub.py
natsio/protocol/operations/sub.py
natsio/protocol/operations/unsub.py
natsio/subscriptions/__init__.py
natsio/subscriptions/core.py
natsio/utils/__init__.py
natsio/utils/json.py
natsio/utils/logger.py
natsio/utils/uuid.py
natsio-0.2.1.dist-info/METADATA
natsio-0.2.1.dist-info/WHEEL
natsio-0.2.1.dist-info/licenses/LICENSE
natsio-0.2.1.dist-info/RECORD
